ram_module.v
module ram_module (
  input [5:0] cpu_address,input [7:0] data_in,input write_enable,input clk,output [7:0] data_out );
  reg [7:0] ram[0:63];
  assign data_out = ram[cpu_address];
  initial begin
    ram[0] = 8'd1;
    ram[1] = 8'd2;  
    ram[2] = 8'd3;  
    ram[3] = 8'd4; 
    ram[4] = 8'd5;  
    ram[5] = 8'd6;  
    ram[6] = 8'd7; 
    ram[7] = 8'd8; 
    ram[8] = 8'd9; 
    ram[9] = 8'd10;
    ram[10] = 8'd11;  
    ram[12] = 8'd13;  
    ram[36] = 8'd37;  
    ram[40] =8'd41;  
    ram[44] = 8'd45;  
    ram[48] = 8'd49;  
    ram[52] = 8'd53;  
    ram[54] = 8'd55;  
    ram[58] = 8'd59;  
    ram[60] = 8'd61;  
    ram[61] = 8'd62;  
    ram[62] = 8'd63;  
    ram[63] = 8'd64;  
  end
  always @(posedge clk) begin
    if (write_enable) 
    ram[cpu_address] = data_in;
  end
endmodule

cache2.v
`include "ram_module.v"
module cache(
  input clk,
  input reset,
  input read, write,
  input [7:0] data_write_cache,
  input [5:0] cpu_address,
  output reg hit,
  output reg miss,
  output reg [7:0] cache_output,
  output reg [1:0] index
);

  reg [7:0] ram_cac_data;
  reg [7:0] cache_hit_data;
  reg [7:0] cache_data[3:0][3:0];
  reg [3:0] cache_tag[3:0][3:0];
  reg valid[3:0][3:0];
  reg found, count;
  reg [1:0] mem, nf;
  wire [7:0] ram_data;

  integer i, j;


  // Instantiate RAM module
  reg ram_write_enable;
  reg [7:0] ram_data_in;
  ram_module ram_inst (
    .cpu_address(cpu_address),
    .data_in(ram_data_in),
    .clk(clk),
    .write_enable(ram_write_enable),
    .data_out(ram_data)
  );

  always @(posedge clk or posedge reset) begin
    if (reset) begin
      for (i = 0; i < 4; i = i + 1)
        for (j = 0; j < 4; j = j + 1) begin
          cache_data[i][j] <= 8'bx;
          cache_tag[i][j] <= 4'bx;
          valid[i][j] <= 0;
        end
      hit <= 0;
      miss <= 0;
      ram_cac_data <= 8'bx;
      cache_output<=8'bx;
      nf <= 0;
    end 
    
    else if (read && !write) begin
      index = cpu_address[1:0];  
      found = 0;
      count = 0;
      mem = 0;
      ram_write_enable = 0;

      for (i = 0; i < 4; i = i + 1) begin           //   4 way checking
        if (!found && cache_tag[i][index] == cpu_address[5:2]) begin
          hit = 1;
          miss = 0;
          cache_hit_data = cache_data[i][index];
          ram_cac_data=8'bx;
          found = 1;
        end
      end
      

      if (!found) begin     // 4 way checking with empty cache
        for (i = 0; i < 4; i = i + 1) begin
          if (!count && valid[i][index] == 0) begin
            miss = 1;
            hit = 0;
            count = 1;
            mem = i;
            valid[i][index] = 1;
            cache_tag[mem][index] = cpu_address[5:2];
            cache_data[mem][index] = ram_data;
            ram_cac_data = cache_data[mem][index]; 
          end
        end
        
        if (!count) begin // if both fails then replacement(FIFO)
          miss = 1;
          hit = 0;
          count <= 1;
          mem = nf; 
          nf = nf + 1; 
          cache_tag[mem][index] = cpu_address[5:2];
          cache_data[mem][index] = ram_data;
          ram_cac_data = cache_data[mem][index];  
        end
      end
    end 



    else if (!read && write) begin // write operation
      index = cpu_address[1:0];  
      found = 0;
      count = 0;
      mem = 0;
      ram_data_in = data_write_cache;
      ram_write_enable = 1;

      for (i = 0; i < 4; i = i + 1) begin
        if (!found && cache_tag[i][index] == cpu_address[5:2]) begin
          hit = 1;
          miss = 0;
          cache_data[i][index] = data_write_cache;
          ram_cac_data=8'bx;
          cache_hit_data = cache_data[i][index];
          found = 1;
        end
      end

      if (!found) begin
        for (i = 0; i < 4; i = i + 1) begin
          if (!count && valid[i][index] == 0) begin
            miss = 1;
            hit = 0;
            count = 1;
            mem = i;
            valid[i][index] = 1;
            cache_tag[mem][index] = cpu_address[5:2];
            cache_data[mem][index] = data_write_cache;
            ram_cac_data =cache_data[mem][index]; 
          end
        end

        if (!count) begin
          miss = 1;
          hit = 0;
          count <= 1;
          mem = nf; 
          nf = nf + 1; 
          cache_tag[mem][index] = cpu_address[5:2];
          cache_data[mem][index] = data_write_cache;
          ram_cac_data = cache_data[mem][index]; 
        end
      end
    end
    
  if(!hit)
  cache_output=ram_cac_data;
  
  else
  cache_output=cache_hit_data;
  
  
  end
endmodule

cache2tb.v
module qwe();
  reg reset, clk, read, write;
  reg [5:0] cpu_address;
  reg [7:0] data_write_cache;
  wire hit, miss;
  wire [7:0]cache_output;
  wire [1:0] index;

  // Instantiate the cache (which internally uses the RAM module)
  cache dut (
    .reset(reset),
    .clk(clk),
    .read(read),
    .write(write),
    .data_write_cache(data_write_cache),
    .cpu_address(cpu_address),
    .hit(hit),
    .miss(miss),
    .cache_output(cache_output),
    .index(index)
  );

  always #5 clk = ~clk;

  initial begin
    clk = 0;
    reset = 1;

    $dumpfile("cache4.vcd");    // Output VCD file
    $dumpvars(0, qwe);
    
    // Dump internal variables of cache
    $dumpvars(1, dut.cache_data[0][0], dut.cache_data[0][1], dut.cache_data[0][2], dut.cache_data[0][3]);
    $dumpvars(1, dut.cache_data[1][0], dut.cache_data[1][1], dut.cache_data[1][2], dut.cache_data[1][3]);
    $dumpvars(1, dut.cache_data[2][0], dut.cache_data[2][1], dut.cache_data[2][2], dut.cache_data[2][3]);
    $dumpvars(1, dut.cache_data[3][0], dut.cache_data[3][1], dut.cache_data[3][2], dut.cache_data[3][3]);
    $dumpvars(1, dut.ram_cac_data);
    $dumpvars(1, dut.valid[0][0], dut.valid[1][0], dut.valid[2][0], dut.valid[3][0]);
    $dumpvars(1, dut.valid[0][1]);

    #15 reset = 0;

    // READ operations
    read = 1; write = 0;
    cpu_address = 6'b000000; //0
    #10 cpu_address = 6'b000001; //01
    #10 cpu_address = 6'b000000; //0
    #10 
    
    read = 0; 
    write = 1;
    
    cpu_address = 6'b000000; //0
    data_write_cache = 8'b11111111; //255
   #10 read = 1; write = 0;
    cpu_address = 6'b000100;//4
    #10 cpu_address = 6'b001000;//8
    #10 cpu_address = 6'b001100;//12
    #10 cpu_address = 6'b100100;//36
    #10 cpu_address = 6'b101000;//40
    

    #120 $finish;
  end
endmodule

cache4.vcd
$date
	Sun May 18 18:27:10 2025
$end
$version
	Icarus Verilog
$end
$timescale
	1s
$end
$scope module qwe $end
$var wire 1 ! miss $end
$var wire 2 " index [1:0] $end
$var wire 1 # hit $end
$var wire 8 $ cache_output [7:0] $end
$var reg 1 % clk $end
$var reg 6 & cpu_address [5:0] $end
$var reg 8 ' data_write_cache [7:0] $end
$var reg 1 ( read $end
$var reg 1 ) reset $end
$var reg 1 * write $end
$scope module dut $end
$var wire 1 % clk $end
$var wire 6 + cpu_address [5:0] $end
$var wire 8 , data_write_cache [7:0] $end
$var wire 1 ( read $end
$var wire 1 ) reset $end
$var wire 1 * write $end
$var wire 8 - ram_data [7:0] $end
$var reg 8 . cache_hit_data [7:0] $end
$var reg 8 / cache_output [7:0] $end
$var reg 1 0 count $end
$var reg 1 1 found $end
$var reg 1 # hit $end
$var reg 2 2 index [1:0] $end
$var reg 2 3 mem [1:0] $end
$var reg 1 ! miss $end
$var reg 2 4 nf [1:0] $end
$var reg 8 5 ram_cac_data [7:0] $end
$var reg 8 6 ram_data_in [7:0] $end
$var reg 1 7 ram_write_enable $end
$var integer 32 8 i [31:0] $end
$var integer 32 9 j [31:0] $end
$scope module ram_inst $end
$var wire 1 % clk $end
$var wire 6 : cpu_address [5:0] $end
$var wire 8 ; data_in [7:0] $end
$var wire 8 < data_out [7:0] $end
$var wire 1 7 write_enable $end
$upscope $end
$upscope $end
$upscope $end
$scope module qwe $end
$scope module dut $end
$var reg 8 = \cache_data[0] [7:0] $end
$upscope $end
$upscope $end
$scope module qwe $end
$scope module dut $end
$var reg 8 > \cache_data[1] [7:0] $end
$upscope $end
$upscope $end
$scope module qwe $end
$scope module dut $end
$var reg 8 ? \cache_data[2] [7:0] $end
$upscope $end
$upscope $end
$scope module qwe $end
$scope module dut $end
$var reg 8 @ \cache_data[3] [7:0] $end
$upscope $end
$upscope $end
$scope module qwe $end
$scope module dut $end
$var reg 8 A \cache_data[4] [7:0] $end
$upscope $end
$upscope $end
$scope module qwe $end
$scope module dut $end
$var reg 8 B \cache_data[5] [7:0] $end
$upscope $end
$upscope $end
$scope module qwe $end
$scope module dut $end
$var reg 8 C \cache_data[6] [7:0] $end
$upscope $end
$upscope $end
$scope module qwe $end
$scope module dut $end
$var reg 8 D \cache_data[7] [7:0] $end
$upscope $end
$upscope $end
$scope module qwe $end
$scope module dut $end
$var reg 8 E \cache_data[8] [7:0] $end
$upscope $end
$upscope $end
$scope module qwe $end
$scope module dut $end
$var reg 8 F \cache_data[9] [7:0] $end
$upscope $end
$upscope $end
$scope module qwe $end
$scope module dut $end
$var reg 8 G \cache_data[10] [7:0] $end
$upscope $end
$upscope $end
$scope module qwe $end
$scope module dut $end
$var reg 8 H \cache_data[11] [7:0] $end
$upscope $end
$upscope $end
$scope module qwe $end
$scope module dut $end
$var reg 8 I \cache_data[12] [7:0] $end
$upscope $end
$upscope $end
$scope module qwe $end
$scope module dut $end
$var reg 8 J \cache_data[13] [7:0] $end
$upscope $end
$upscope $end
$scope module qwe $end
$scope module dut $end
$var reg 8 K \cache_data[14] [7:0] $end
$upscope $end
$upscope $end
$scope module qwe $end
$scope module dut $end
$var reg 8 L \cache_data[15] [7:0] $end
$upscope $end
$upscope $end
$scope module qwe $end
$scope module dut $end
$var reg 1 M \valid[0] $end
$upscope $end
$upscope $end
$scope module qwe $end
$scope module dut $end
$var reg 1 N \valid[4] $end
$upscope $end
$upscope $end
$scope module qwe $end
$scope module dut $end
$var reg 1 O \valid[8] $end
$upscope $end
$upscope $end
$scope module qwe $end
$scope module dut $end
$var reg 1 P \valid[12] $end
$upscope $end
$upscope $end
$scope module qwe $end
$scope module dut $end
$var reg 1 Q \valid[1] $end
$upscope $end
$upscope $end
$enddefinitions $end
#0
$dumpvars
0Q
0P
0O
0N
0M
bx L
bx K
bx J
bx I
bx H
bx G
bx F
bx E
bx D
bx C
bx B
bx A
bx @
bx ?
bx >
bx =
bx <
bx ;
bx :
b100 9
b100 8
x7
bx 6
bx 5
b0 4
bx 3
bx 2
x1
x0
bx /
bx .
bx -
bx ,
bx +
x*
1)
x(
bx '
bx &
0%
bx $
0#
bx "
0!
$end
#5
bx L
bx K
bx J
0P
bx I
bx H
bx G
bx F
0O
bx E
bx D
bx C
bx B
0N
bx A
bx @
bx ?
0Q
bx >
0M
bx =
b100 9
b100 8
1%
#10
0%
#15
b1 $
b1 /
b1 5
b1 =
1M
1!
b100 8
07
b0 3
10
01
b0 "
b0 2
1%
b1 -
b1 <
b0 &
b0 +
b0 :
0*
1(
0)
#20
0%
#25
b10 $
b10 /
b10 5
b10 >
1Q
b100 8
10
b1 "
b1 2
1%
b10 -
b10 <
b1 &
b1 +
b1 :
#30
0%
#35
b1 $
b1 /
11
bx 5
b1 .
0!
1#
b100 8
00
b0 "
b0 2
1%
b1 -
b1 <
b0 &
b0 +
b0 :
#40
0%
#45
b11111111 -
b11111111 <
b11111111 $
b11111111 /
b11111111 .
b11111111 =
b100 8
17
b11111111 6
b11111111 ;
11
1%
b11111111 '
b11111111 ,
1*
0(
#50
0%
#55
b101 $
b101 /
b101 5
b101 A
1N
b1 3
10
0#
1!
b100 8
07
01
1%
b101 -
b101 <
b100 &
b100 +
b100 :
0*
1(
#60
0%
#65
b1001 $
b1001 /
b1001 5
b1001 E
1O
b100 8
b10 3
10
1%
b1001 -
b1001 <
b1000 &
b1000 +
b1000 :
#70
0%
#75
b1101 $
b1101 /
b1101 5
b1101 I
1P
b100 8
b11 3
10
1%
b1101 -
b1101 <
b1100 &
b1100 +
b1100 :
#80
0%
#85
b100101 $
b100101 /
b100101 5
b100101 =
b1 4
b100 8
b0 3
10
1%
b100101 -
b100101 <
b100100 &
b100100 +
b100100 :
#90
0%
#95
b101001 $
b101001 /
b101001 5
b101001 A
b10 4
b1 3
b100 8
10
1%
b101001 -
b101001 <
b101000 &
b101000 +
b101000 :
#100
0%
#105
11
bx 5
b101001 .
0!
1#
b100 8
b0 3
00
1%
#110
0%
#115
b100 8
11
1%
#120
0%
#125
b100 8
11
1%
#130
0%
#135
b100 8
11
1%
#140
0%
#145
b100 8
11
1%
#150
0%
#155
b100 8
11
1%
#160
0%
#165
b100 8
11
1%
#170
0%
#175
b100 8
11
1%
#180
0%
#185
b100 8
11
1%
#190
0%
#195
b100 8
11
1%
#200
0%
#205
b100 8
11
1%
#210
0%
#215
b100 8
11
1%
